pyapollo/__init__.py
pyapollo/__init__.pyc
pyapollo/apollo_client.py
pyapollo/test.py
pyapollo/cache/__init__.py
pyapollo/cache/__init__.pyc
pyapollo/cache/basecache.py
pyapollo/cache/basecache.pyc
pyapollo/cache/filecache.py
pyapollo/cache/filecache.pyc
pyapollo-0.0.7.dist-info/METADATA
pyapollo-0.0.7.dist-info/RECORD
pyapollo-0.0.7.dist-info/WHEEL
pyapollo-0.0.7.dist-info/top_level.txt
